pillow_raw_opener-0.2.1.dist-info/licenses/LICENSE
raw_pillow_opener/__init__.py
pillow_raw_opener-0.2.1.dist-info/METADATA
pillow_raw_opener-0.2.1.dist-info/WHEEL
pillow_raw_opener-0.2.1.dist-info/top_level.txt
pillow_raw_opener-0.2.1.dist-info/RECORD
