Metadata-Version: 2.4
Name: pillow-raw-opener
Version: 0.2.1
Summary: raw-pillow-opener is a simple raw image opener for Pillow base on rawpy.
Home-page: https://github.com/chitkiu/raw-pillow-opener
Download-URL: https://github.com/chitkiu/raw-pillow-opener/archive/v0.2.1.tar.gz
Author: Samuel Duann
Author-email: adamgic@gmail.com
License: MIT
Keywords: nef,raw,Pillow
Classifier: Development Status :: 4 - Beta
Classifier: Intended Audience :: Developers
Classifier: Natural Language :: English
Classifier: License :: OSI Approved :: MIT License
Classifier: Programming Language :: Python :: 3
Classifier: Programming Language :: Python :: 3.9
Classifier: Programming Language :: Python :: 3.10
Classifier: Programming Language :: Python :: 3.11
Classifier: Programming Language :: Python :: 3.12
Classifier: Operating System :: MacOS
Classifier: Operating System :: POSIX
Classifier: Operating System :: Unix
Classifier: Topic :: Multimedia :: Graphics
Classifier: Topic :: Software Development :: Libraries
License-File: LICENSE
Requires-Dist: rawpy==0.25.*
Dynamic: author
Dynamic: author-email
Dynamic: classifier
Dynamic: description
Dynamic: description-content-type
Dynamic: download-url
Dynamic: home-page
Dynamic: keywords
Dynamic: license
Dynamic: license-file
Dynamic: requires-dist
Dynamic: summary
